geosurveymath/__init__.py
geosurveymath/common.py
geosurveymath/geosurveymath.py
geosurveymath-0.0.1.dist-info/licenses/LICENSE
geosurveymath-0.0.1.dist-info/METADATA
geosurveymath-0.0.1.dist-info/WHEEL
geosurveymath-0.0.1.dist-info/entry_points.txt
geosurveymath-0.0.1.dist-info/top_level.txt
geosurveymath-0.0.1.dist-info/RECORD
